[
  {
    "epoch": 1.0,
    "train_loss": 0.7012775449289216,
    "test_accuracy": 0.46875,
    "test_kappa": -0.0625,
    "backbone_lr": 0.0,
    "head_lr": 0.001
  },
  {
    "epoch": 2.0,
    "train_loss": 0.6908788482348124,
    "test_accuracy": 0.4583333333333333,
    "test_kappa": -0.08333333333333326,
    "backbone_lr": 0.0,
    "head_lr": 0.001
  },
  {
    "epoch": 3.0,
    "train_loss": 0.6938209558526675,
    "test_accuracy": 0.4930555555555556,
    "test_kappa": -0.01388888888888884,
    "backbone_lr": 0.0,
    "head_lr": 0.001
  },
  {
    "epoch": 4.0,
    "train_loss": 0.6906047330962287,
    "test_accuracy": 0.4826388888888889,
    "test_kappa": -0.03472222222222232,
    "backbone_lr": 0.0001,
    "head_lr": 0.001
  },
  {
    "epoch": 5.0,
    "train_loss": 0.6877616635627217,
    "test_accuracy": 0.4826388888888889,
    "test_kappa": -0.03472222222222232,
    "backbone_lr": 0.0001,
    "head_lr": 0.001
  },
  {
    "epoch": 6.0,
    "train_loss": 0.675916377041075,
    "test_accuracy": 0.5104166666666666,
    "test_kappa": 0.02083333333333337,
    "backbone_lr": 0.0001,
    "head_lr": 0.001
  },
  {
    "epoch": 7.0,
    "train_loss": 0.6670413298739327,
    "test_accuracy": 0.5,
    "test_kappa": 0.0,
    "backbone_lr": 0.0001,
    "head_lr": 0.001
  },
  {
    "epoch": 8.0,
    "train_loss": 0.6536922852198283,
    "test_accuracy": 0.4930555555555556,
    "test_kappa": -0.01388888888888884,
    "backbone_lr": 0.0001,
    "head_lr": 0.001
  },
  {
    "epoch": 9.0,
    "train_loss": 0.6505101604594125,
    "test_accuracy": 0.5208333333333334,
    "test_kappa": 0.04166666666666663,
    "backbone_lr": 0.0001,
    "head_lr": 0.001
  },
  {
    "epoch": 10.0,
    "train_loss": 0.6274186972942617,
    "test_accuracy": 0.5104166666666666,
    "test_kappa": 0.02083333333333337,
    "backbone_lr": 0.0001,
    "head_lr": 0.001
  },
  {
    "epoch": 11.0,
    "train_loss": 0.6295223832130432,
    "test_accuracy": 0.5138888888888888,
    "test_kappa": 0.02777777777777779,
    "backbone_lr": 0.0001,
    "head_lr": 0.001
  },
  {
    "epoch": 12.0,
    "train_loss": 0.6136106045709716,
    "test_accuracy": 0.5173611111111112,
    "test_kappa": 0.03472222222222221,
    "backbone_lr": 0.0001,
    "head_lr": 0.001
  },
  {
    "epoch": 13.0,
    "train_loss": 0.6092165754073195,
    "test_accuracy": 0.5173611111111112,
    "test_kappa": 0.03472222222222221,
    "backbone_lr": 0.0001,
    "head_lr": 0.001
  },
  {
    "epoch": 14.0,
    "train_loss": 0.600968808763557,
    "test_accuracy": 0.5277777777777778,
    "test_kappa": 0.05555555555555558,
    "backbone_lr": 0.0001,
    "head_lr": 0.001
  },
  {
    "epoch": 15.0,
    "train_loss": 0.5921135027375486,
    "test_accuracy": 0.5069444444444444,
    "test_kappa": 0.01388888888888884,
    "backbone_lr": 0.0001,
    "head_lr": 0.001
  },
  {
    "epoch": 16.0,
    "train_loss": 0.5935657417608632,
    "test_accuracy": 0.5208333333333334,
    "test_kappa": 0.04166666666666663,
    "backbone_lr": 0.0001,
    "head_lr": 0.001
  },
  {
    "epoch": 17.0,
    "train_loss": 0.5966446292069223,
    "test_accuracy": 0.5243055555555556,
    "test_kappa": 0.04861111111111116,
    "backbone_lr": 0.0001,
    "head_lr": 0.001
  },
  {
    "epoch": 18.0,
    "train_loss": 0.5843400040434467,
    "test_accuracy": 0.5173611111111112,
    "test_kappa": 0.03472222222222221,
    "backbone_lr": 0.0001,
    "head_lr": 0.001
  },
  {
    "epoch": 19.0,
    "train_loss": 0.5817900519404147,
    "test_accuracy": 0.5138888888888888,
    "test_kappa": 0.02777777777777779,
    "backbone_lr": 0.0001,
    "head_lr": 0.001
  },
  {
    "epoch": 20.0,
    "train_loss": 0.5772408487068282,
    "test_accuracy": 0.5034722222222222,
    "test_kappa": 0.00694444444444442,
    "backbone_lr": 0.0001,
    "head_lr": 0.001
  },
  {
    "epoch": 21.0,
    "train_loss": 0.5768776958187422,
    "test_accuracy": 0.5104166666666666,
    "test_kappa": 0.02083333333333337,
    "backbone_lr": 0.0001,
    "head_lr": 0.001
  },
  {
    "epoch": 22.0,
    "train_loss": 0.5663733602397971,
    "test_accuracy": 0.5277777777777778,
    "test_kappa": 0.05555555555555558,
    "backbone_lr": 0.0001,
    "head_lr": 0.001
  }
]