[
  {
    "epoch": 1.0,
    "train_loss": 0.9613008400668268,
    "test_accuracy": 0.5,
    "test_kappa": 0.0
  },
  {
    "epoch": 2.0,
    "train_loss": 0.7363948765008346,
    "test_accuracy": 0.5,
    "test_kappa": 0.0
  },
  {
    "epoch": 3.0,
    "train_loss": 0.6968359304511029,
    "test_accuracy": 0.5,
    "test_kappa": 0.0
  },
  {
    "epoch": 4.0,
    "train_loss": 0.7080145156901816,
    "test_accuracy": 0.5,
    "test_kappa": 0.0
  },
  {
    "epoch": 5.0,
    "train_loss": 0.7039904967598293,
    "test_accuracy": 0.5,
    "test_kappa": 0.0
  },
  {
    "epoch": 6.0,
    "train_loss": 0.6922617326612058,
    "test_accuracy": 0.5344827586206896,
    "test_kappa": 0.06896551724137934
  },
  {
    "epoch": 7.0,
    "train_loss": 0.689228151673856,
    "test_accuracy": 0.5,
    "test_kappa": 0.0
  },
  {
    "epoch": 8.0,
    "train_loss": 0.7270839136579762,
    "test_accuracy": 0.5,
    "test_kappa": 0.0
  },
  {
    "epoch": 9.0,
    "train_loss": 0.7509079077969427,
    "test_accuracy": 0.5689655172413793,
    "test_kappa": 0.13793103448275867
  },
  {
    "epoch": 10.0,
    "train_loss": 0.7271758245385211,
    "test_accuracy": 0.5,
    "test_kappa": 0.0
  },
  {
    "epoch": 11.0,
    "train_loss": 0.7017329920893131,
    "test_accuracy": 0.5,
    "test_kappa": 0.0
  },
  {
    "epoch": 12.0,
    "train_loss": 0.7268199625222579,
    "test_accuracy": 0.5517241379310345,
    "test_kappa": 0.10344827586206895
  },
  {
    "epoch": 13.0,
    "train_loss": 0.6897747682488483,
    "test_accuracy": 0.5,
    "test_kappa": 0.0
  },
  {
    "epoch": 14.0,
    "train_loss": 0.6815115576205046,
    "test_accuracy": 0.5344827586206896,
    "test_kappa": 0.06896551724137934
  },
  {
    "epoch": 15.0,
    "train_loss": 0.6636076486628989,
    "test_accuracy": 0.5344827586206896,
    "test_kappa": 0.06896551724137934
  },
  {
    "epoch": 16.0,
    "train_loss": 0.6188926206982654,
    "test_accuracy": 0.5689655172413793,
    "test_kappa": 0.13793103448275867
  },
  {
    "epoch": 17.0,
    "train_loss": 0.6761043183181596,
    "test_accuracy": 0.5344827586206896,
    "test_kappa": 0.06896551724137934
  },
  {
    "epoch": 18.0,
    "train_loss": 0.5490561583767767,
    "test_accuracy": 0.5862068965517241,
    "test_kappa": 0.1724137931034483
  },
  {
    "epoch": 19.0,
    "train_loss": 0.612474178749582,
    "test_accuracy": 0.5689655172413793,
    "test_kappa": 0.13793103448275867
  },
  {
    "epoch": 20.0,
    "train_loss": 0.5868809013263039,
    "test_accuracy": 0.6206896551724138,
    "test_kappa": 0.24137931034482762
  },
  {
    "epoch": 21.0,
    "train_loss": 0.592548085813937,
    "test_accuracy": 0.5,
    "test_kappa": 0.0
  },
  {
    "epoch": 22.0,
    "train_loss": 0.6105692801268204,
    "test_accuracy": 0.5862068965517241,
    "test_kappa": 0.1724137931034483
  },
  {
    "epoch": 23.0,
    "train_loss": 0.5694063609061034,
    "test_accuracy": 0.5344827586206896,
    "test_kappa": 0.06896551724137934
  },
  {
    "epoch": 24.0,
    "train_loss": 0.49244251614031587,
    "test_accuracy": 0.5689655172413793,
    "test_kappa": 0.13793103448275867
  },
  {
    "epoch": 25.0,
    "train_loss": 0.5038831773011581,
    "test_accuracy": 0.5517241379310345,
    "test_kappa": 0.10344827586206895
  },
  {
    "epoch": 26.0,
    "train_loss": 0.494552859534388,
    "test_accuracy": 0.6724137931034483,
    "test_kappa": 0.3448275862068966
  },
  {
    "epoch": 27.0,
    "train_loss": 0.47153349285540375,
    "test_accuracy": 0.7241379310344828,
    "test_kappa": 0.4482758620689655
  },
  {
    "epoch": 28.0,
    "train_loss": 0.44682803205821825,
    "test_accuracy": 0.7241379310344828,
    "test_kappa": 0.4482758620689655
  },
  {
    "epoch": 29.0,
    "train_loss": 0.4719151266243147,
    "test_accuracy": 0.7586206896551724,
    "test_kappa": 0.5172413793103448
  },
  {
    "epoch": 30.0,
    "train_loss": 0.4574380532554958,
    "test_accuracy": 0.7586206896551724,
    "test_kappa": 0.5172413793103448
  }
]